montycat/__init__.py
montycat/core/__init__.py
montycat/core/engine.py
montycat/core/schema.py
montycat/core/store.py
montycat/core/tools.py
montycat/core/utils.py
montycat/store_classes/__init__.py
montycat/store_classes/kv.py
montycat/store_functions/__init__.py
montycat/store_functions/store_generic_functions.py
montycat-0.1.39.dist-info/METADATA
montycat-0.1.39.dist-info/WHEEL
montycat-0.1.39.dist-info/top_level.txt
montycat-0.1.39.dist-info/RECORD
