Metadata-Version: 2.4
Name: montycat
Version: 0.1.39
Summary: A Python client for MontyCat, NoSQL store utilizing Data Mesh architecture.
Author: MontyGovernance
Author-email: eugene.and.monty@gmail.com
Classifier: Programming Language :: Python :: 3
Classifier: License :: OSI Approved :: MIT License
Classifier: Operating System :: OS Independent
Requires-Python: >=3.9
Requires-Dist: orjson
Requires-Dist: xxhash
Requires-Dist: asyncio
Dynamic: author
Dynamic: author-email
Dynamic: classifier
Dynamic: description
Dynamic: description-content-type
Dynamic: requires-dist
Dynamic: requires-python
Dynamic: summary
